{"totalResultsCount":78,"geonames":[{"adminCode1":"NC","lng":"-79.00603","geonameId":6941080,"toponymName":"Fort Bragg","countryId":"6252001","fcl":"P","population":29183,"countryCode":"US","name":"Fort Bragg","fclName":"city, village,...","adminCodes1":{"ISO3166_2":"NC"},"countryName":"United States","fcodeName":"populated place","adminName1":"North Carolina","lat":"35.139","fcode":"PPL"},{"adminCode1":"CA","lng":"-123.80529","geonameId":5350039,"toponymName":"Fort Bragg","countryId":"6252001","fcl":"P","population":7289,"countryCode":"US","name":"Fort Bragg","fclName":"city, village,...","adminCodes1":{"ISO3166_2":"CA"},"countryName":"United States","fcodeName":"populated place","adminName1":"California","lat":"39.44572","fcode":"PPL"},{"adminCode1":"CA","lng":"-123.7953","geonameId":5350040,"toponymName":"Fort Bragg Airport","countryId":"6252001","fcl":"S","population":0,"countryCode":"US","name":"Fort Bragg Airport","fclName":"spot, building, farm","adminCodes1":{"ISO3166_2":"CA"},"countryName":"United States","fcodeName":"airport","adminName1":"California","lat":"39.4715","fcode":"AIRP"},{"adminCode1":"WI","lng":"-88.52178","geonameId":5253506,"toponymName":"Fort Bragg Monument Park","countryId":"6252001","fcl":"L","population":0,"countryCode":"US","name":"Fort Bragg Monument Park","fclName":"parks,area, ...","adminCodes1":{"ISO3166_2":"WI"},"countryName":"United States","fcodeName":"park","adminName1":"Wisconsin","lat":"44.02443","fcode":"PRK"},{"adminCode1":"NC","lng":"-79.22746","geonameId":7170459,"toponymName":"Township of Fort Bragg Military Reservation","countryId":"6252001","fcl":"A","population":0,"countryCode":"US","name":"Township of Fort Bragg Military Reservation","fclName":"country, state, region,...","adminCodes1":{"ISO3166_2":"NC"},"countryName":"United States","fcodeName":"third-order administrative division","adminName1":"North Carolina","lat":"35.11511","fcode":"ADM3"},{"adminCode1":"CA","lng":"-123.8034","geonameId":11788329,"toponymName":"City of Fort Bragg","countryId":"6252001","fcl":"A","population":0,"countryCode":"US","name":"City of Fort Bragg","fclName":"country, state, region,...","adminCodes1":{"ISO3166_2":"CA"},"countryName":"United States","fcodeName":"third-order administrative division","adminName1":"California","lat":"39.44148","fcode":"ADM3"},{"adminCode1":"CA","lng":"-123.7753","geonameId":6941853,"toponymName":"Fort Bragg's Noyo Harbor","countryId":"6252001","fcl":"H","population":0,"countryCode":"US","name":"Fort Bragg's Noyo Harbor","fclName":"stream, lake, ...","adminCodes1":{"ISO3166_2":"CA"},"countryName":"United States","fcodeName":"lake","adminName1":"California","lat":"39.5152","fcode":"LK"},{"adminCode1":"CA","lng":"-123.7876","geonameId":5350047,"toponymName":"Fort Bragg High School","countryId":"6252001","fcl":"S","population":0,"countryCode":"US","name":"Fort Bragg High School","fclName":"spot, building, farm","adminCodes1":{"ISO3166_2":"CA"},"countryName":"United States","fcodeName":"school","adminName1":"California","lat":"39.43778","fcode":"SCH"},{"adminCode1":"CA","lng":"-123.78113","geonameId":5361679,"toponymName":"KDAC-AM (Fort Bragg)","countryId":"6252001","fcl":"S","population":0,"countryCode":"US","name":"KDAC-AM (Fort Bragg)","fclName":"spot, building, farm","adminCodes1":{"ISO3166_2":"CA"},"countryName":"United States","fcodeName":"tower","adminName1":"California","lat":"39.44295","fcode":"TOWR"},{"adminCode1":"NC","lng":"-79.00275","geonameId":7259769,"toponymName":"Fort Bragg  (historical)","countryId":"6252001","fcl":"P","population":0,"countryCode":"US","name":"Fort Bragg  (historical)","fclName":"city, village,...","adminCodes1":{"ISO3166_2":"NC"},"countryName":"United States","fcodeName":"populated place","adminName1":"North Carolina","lat":"35.13717","fcode":"PPL"},{"adminCode1":"CA","lng":"-123.80678","geonameId":12076714,"toponymName":"Noyo River Bridge","countryId":"6252001","fcl":"S","population":0,"countryCode":"US","name":"Noyo River Bridge","fclName":"spot, building, farm","adminCodes1":{"ISO3166_2":"CA"},"countryName":"United States","fcodeName":"bridge","adminName1":"California","lat":"39.4276","fcode":"BDG"},{"adminCode1":"NC","lng":"-79.20683","geonameId":7838844,"toponymName":"Battle of Monroe\u2019s Crossroads Monument","countryId":"6252001","fcl":"S","population":0,"countryCode":"US","name":"Battle of Monroe\u2019s Crossroads Monument","fclName":"spot, building, farm","adminCodes1":{"ISO3166_2":"NC"},"countryName":"United States","fcodeName":"monument","adminName1":"North Carolina","lat":"35.12247","fcode":"MNMT"},{"adminCode1":"NC","lng":"-79.23503","geonameId":4456463,"toponymName":"Blues Mountain","countryId":"6252001","fcl":"T","population":0,"countryCode":"US","name":"Blues Mountain","fclName":"mountain,hill,rock,... ","adminCodes1":{"ISO3166_2":"NC"},"countryName":"United States","fcodeName":"mountain","adminName1":"North Carolina","lat":"35.09266","fcode":"MT"},{"adminCode1":"NC","lng":"-79.23114","geonameId":4458982,"toponymName":"Campbells Crossroad","countryId":"6252001","fcl":"P","population":0,"countryCode":"US","name":"Campbells Crossroad","fclName":"city, village,...","adminCodes1":{"ISO3166_2":"NC"},"countryName":"United States","fcodeName":"populated place","adminName1":"North Carolina","lat":"35.08711","fcode":"PPL"},{"adminCode1":"NC","lng":"-79.24058","geonameId":4472751,"toponymName":"Inverness","countryId":"6252001","fcl":"P","population":0,"countryCode":"US","name":"Inverness","fclName":"city, village,...","adminCodes1":{"ISO3166_2":"NC"},"countryName":"United States","fcodeName":"populated place","adminName1":"North Carolina","lat":"35.18155","fcode":"PPL"},{"adminCode1":"NC","lng":"-79.24142","geonameId":4473606,"toponymName":"Johnson Mountain","countryId":"6252001","fcl":"T","population":0,"countryCode":"US","name":"Johnson Mountain","fclName":"mountain,hill,rock,... ","adminCodes1":{"ISO3166_2":"NC"},"countryName":"United States","fcodeName":"mountain","adminName1":"North Carolina","lat":"35.14155","fcode":"MT"},{"adminCode1":"NC","lng":"-79.18975","geonameId":4466177,"toponymName":"Finlayson Mountain","countryId":"6252001","fcl":"T","population":0,"countryCode":"US","name":"Finlayson Mountain","fclName":"mountain,hill,rock,... ","adminCodes1":{"ISO3166_2":"NC"},"countryName":"United States","fcodeName":"mountain","adminName1":"North Carolina","lat":"35.07461","fcode":"MT"},{"adminCode1":"NC","lng":"-79.19086","geonameId":4467513,"toponymName":"Gaddys Mountain","countryId":"6252001","fcl":"T","population":0,"countryCode":"US","name":"Gaddys Mountain","fclName":"mountain,hill,rock,... ","adminCodes1":{"ISO3166_2":"NC"},"countryName":"United States","fcodeName":"mountain","adminName1":"North Carolina","lat":"35.12433","fcode":"MT"},{"adminCode1":"NC","lng":"-79.14392","geonameId":4456110,"toponymName":"Black Ford","countryId":"6252001","fcl":"R","population":0,"countryCode":"US","name":"Black Ford","fclName":"road, railroad ","adminCodes1":{"ISO3166_2":"NC"},"countryName":"United States","fcodeName":"road junction","adminName1":"North Carolina","lat":"35.08989","fcode":"RDJCT"},{"adminCode1":"NC","lng":"-79.13392","geonameId":4486766,"toponymName":"Puppy Creek Ford","countryId":"6252001","fcl":"R","population":0,"countryCode":"US","name":"Puppy Creek Ford","fclName":"road, railroad ","adminCodes1":{"ISO3166_2":"NC"},"countryName":"United States","fcodeName":"road junction","adminName1":"North Carolina","lat":"35.06877","fcode":"RDJCT"},{"adminCode1":"CA","lng":"-123.79476","geonameId":5386864,"toponymName":"Redwood Elementary School","countryId":"6252001","fcl":"S","population":0,"countryCode":"US","name":"Redwood Elementary School","fclName":"spot, building, farm","adminCodes1":{"ISO3166_2":"CA"},"countryName":"United States","fcodeName":"school","adminName1":"California","lat":"39.43739","fcode":"SCH"},{"adminCode1":"CA","lng":"-123.808","geonameId":6491355,"toponymName":"Coast Motel - Fort Bragg","countryId":"6252001","fcl":"S","population":0,"countryCode":"US","name":"Coast Motel - Fort Bragg","fclName":"spot, building, farm","adminCodes1":{"ISO3166_2":"CA"},"countryName":"United States","fcodeName":"hotel","adminName1":"California","lat":"39.4155","fcode":"HTL"},{"adminCode1":"CA","lng":"-123.8064","geonameId":6532772,"toponymName":"Super 8 Motel   Fort Bragg","countryId":"6252001","fcl":"S","population":0,"countryCode":"US","name":"Super 8 Motel   Fort Bragg","fclName":"spot, building, farm","adminCodes1":{"ISO3166_2":"CA"},"countryName":"United States","fcodeName":"hotel","adminName1":"California","lat":"39.4296","fcode":"HTL"},{"adminCode1":"CA","lng":"-123.81667","geonameId":6298779,"toponymName":"Fort Bragg","countryId":"6252001","fcl":"S","population":0,"countryCode":"US","name":"Fort Bragg","fclName":"spot, building, farm","adminCodes1":{"ISO3166_2":"CA"},"countryName":"United States","fcodeName":"meteorological station","adminName1":"California","lat":"39.4","fcode":"STNM"},{"adminCode1":"CA","lng":"-123.79842","geonameId":7236238,"toponymName":"Fort Bragg Seventh Day Adventist School","countryId":"6252001","fcl":"S","population":0,"countryCode":"US","name":"Fort Bragg Seventh Day Adventist School","fclName":"spot, building, farm","adminCodes1":{"ISO3166_2":"CA"},"countryName":"United States","fcodeName":"school","adminName1":"California","lat":"39.47246","fcode":"SCH"},{"adminCode1":"CA","lng":"-123.815","geonameId":7270438,"toponymName":"City of Fort Bragg Wastewater Treatment Plant","countryId":"6252001","fcl":"S","population":0,"countryCode":"US","name":"City of Fort Bragg Wastewater Treatment Plant","fclName":"spot, building, farm","adminCodes1":{"ISO3166_2":"CA"},"countryName":"United States","fcodeName":"sewage treatment plant","adminName1":"California","lat":"39.43889","fcode":"SWT"},{"adminCode1":"CA","lng":"-123.57974","geonameId":5361772,"toponymName":"KFWU-TV (Fort Bragg)","countryId":"6252001","fcl":"S","population":0,"countryCode":"US","name":"KFWU-TV (Fort Bragg)","fclName":"spot, building, farm","adminCodes1":{"ISO3166_2":"CA"},"countryName":"United States","fcodeName":"tower","adminName1":"California","lat":"39.69377","fcode":"TOWR"},{"adminCode1":"CA","lng":"-123.75863","geonameId":5361931,"toponymName":"KLLK-FM (Fort Bragg)","countryId":"6252001","fcl":"S","population":0,"countryCode":"US","name":"KLLK-FM (Fort Bragg)","fclName":"spot, building, farm","adminCodes1":{"ISO3166_2":"CA"},"countryName":"United States","fcodeName":"tower","adminName1":"California","lat":"39.46461","fcode":"TOWR"},{"adminCode1":"CA","lng":"-123.73557","geonameId":5362053,"toponymName":"KOZT-FM (Fort Bragg)","countryId":"6252001","fcl":"S","population":0,"countryCode":"US","name":"KOZT-FM (Fort Bragg)","fclName":"spot, building, farm","adminCodes1":{"ISO3166_2":"CA"},"countryName":"United States","fcodeName":"tower","adminName1":"California","lat":"39.40656","fcode":"TOWR"},{"adminCode1":"CA","lng":"-123.76057","geonameId":5362165,"toponymName":"KSAY-FM (Fort Bragg)","countryId":"6252001","fcl":"S","population":0,"countryCode":"US","name":"KSAY-FM (Fort Bragg)","fclName":"spot, building, farm","adminCodes1":{"ISO3166_2":"CA"},"countryName":"United States","fcodeName":"tower","adminName1":"California","lat":"39.46739","fcode":"TOWR"},{"adminCode1":"CA","lng":"-123.8014","geonameId":5362345,"toponymName":"KWSF-FM (Fort Bragg)","countryId":"6252001","fcl":"S","population":0,"countryCode":"US","name":"KWSF-FM (Fort Bragg)","fclName":"spot, building, farm","adminCodes1":{"ISO3166_2":"CA"},"countryName":"United States","fcodeName":"tower","adminName1":"California","lat":"39.38517","fcode":"TOWR"},{"adminCode1":"CA","lng":"-123.80113","geonameId":5350041,"toponymName":"Fort Bragg Branch Mendocino County Library","countryId":"6252001","fcl":"S","population":0,"countryCode":"US","name":"Fort Bragg Branch Mendocino County Library","fclName":"spot, building, farm","adminCodes1":{"ISO3166_2":"CA"},"countryName":"United States","fcodeName":"library","adminName1":"California","lat":"39.44572","fcode":"LIBR"},{"adminCode1":"CA","lng":"-123.80418","geonameId":5350042,"toponymName":"Fort Bragg City Hall","countryId":"6252001","fcl":"S","population":0,"countryCode":"US","name":"Fort Bragg City Hall","fclName":"spot, building, farm","adminCodes1":{"ISO3166_2":"CA"},"countryName":"United States","fcodeName":"building(s)","adminName1":"California","lat":"39.44572","fcode":"BLDG"},{"adminCode1":"CA","lng":"-123.76335","geonameId":5350043,"toponymName":"Fort Bragg Grange","countryId":"6252001","fcl":"S","population":0,"countryCode":"US","name":"Fort Bragg Grange","fclName":"spot, building, farm","adminCodes1":{"ISO3166_2":"CA"},"countryName":"United States","fcodeName":"building(s)","adminName1":"California","lat":"39.516","fcode":"BLDG"},{"adminCode1":"CA","lng":"-123.81446","geonameId":5350044,"toponymName":"Fort Bragg Landing","countryId":"6252001","fcl":"S","population":0,"countryCode":"US","name":"Fort Bragg Landing","fclName":"spot, building, farm","adminCodes1":{"ISO3166_2":"CA"},"countryName":"United States","fcodeName":"","adminName1":"California","lat":"39.44045"},{"adminCode1":"CA","lng":"-123.79723","geonameId":5350045,"toponymName":"Fort Bragg Middle School","countryId":"6252001","fcl":"S","population":0,"countryCode":"US","name":"Fort Bragg Middle School","fclName":"spot, building, farm","adminCodes1":{"ISO3166_2":"CA"},"countryName":"United States","fcodeName":"school","adminName1":"California","lat":"39.44807","fcode":"SCH"},{"adminCode1":"CA","lng":"-123.80307","geonameId":5350046,"toponymName":"Fort Bragg Post Office","countryId":"6252001","fcl":"S","population":0,"countryCode":"US","name":"Fort Bragg Post Office","fclName":"spot, building, farm","adminCodes1":{"ISO3166_2":"CA"},"countryName":"United States","fcodeName":"post office","adminName1":"California","lat":"39.44433","fcode":"PO"},{"adminCode1":"CA","lng":"-123.80029","geonameId":5350048,"toponymName":"Fort Bragg Seventh Day Adventist Church","countryId":"6252001","fcl":"S","population":0,"countryCode":"US","name":"Fort Bragg Seventh Day Adventist Church","fclName":"spot, building, farm","adminCodes1":{"ISO3166_2":"CA"},"countryName":"United States","fcodeName":"church","adminName1":"California","lat":"39.44656","fcode":"CH"},{"adminCode1":"CA","lng":"-123.80632","geonameId":7722370,"toponymName":"Fort Bragg Volunteer Fire Department Station 830","countryId":"6252001","fcl":"S","population":0,"countryCode":"US","name":"Fort Bragg Volunteer Fire Department Station 830","fclName":"spot, building, farm","adminCodes1":{"ISO3166_2":"CA"},"countryName":"United States","fcodeName":"building(s)","adminName1":"California","lat":"39.44228","fcode":"BLDG"},{"adminCode1":"CA","lng":"-123.79538","geonameId":7722709,"toponymName":"Fort Bragg Volunteer Fire Department Station 2","countryId":"6252001","fcl":"S","population":0,"countryCode":"US","name":"Fort Bragg Volunteer Fire Department Station 2","fclName":"spot, building, farm","adminCodes1":{"ISO3166_2":"CA"},"countryName":"United States","fcodeName":"building(s)","adminName1":"California","lat":"39.41794","fcode":"BLDG"},{"adminCode1":"CA","lng":"-123.80559","geonameId":7722801,"toponymName":"California Department of Forestry and Fire Protection Fort Bragg","countryId":"6252001","fcl":"S","population":0,"countryCode":"US","name":"California Department of Forestry and Fire Protection Fort Bragg","fclName":"spot, building, farm","adminCodes1":{"ISO3166_2":"CA"},"countryName":"United States","fcodeName":"building(s)","adminName1":"California","lat":"39.45081","fcode":"BLDG"},{"adminCode1":"CA","lng":"-123.80398","geonameId":9684391,"toponymName":"Fort Bragg Police Department","countryId":"6252001","fcl":"S","population":0,"countryCode":"US","name":"Fort Bragg Police Department","fclName":"spot, building, farm","adminCodes1":{"ISO3166_2":"CA"},"countryName":"United States","fcodeName":"building(s)","adminName1":"California","lat":"39.43238","fcode":"BLDG"},{"adminCode1":"CA","lng":"-123.8059","geonameId":9862443,"toponymName":"Holiday Inn Express Fort Bragg","countryId":"6252001","fcl":"S","population":0,"countryCode":"US","name":"Holiday Inn Express Fort Bragg","fclName":"spot, building, farm","adminCodes1":{"ISO3166_2":"CA"},"countryName":"United States","fcodeName":"hotel","adminName1":"California","lat":"39.41976","fcode":"HTL"},{"adminCode1":"CA","lng":"-123.80608","geonameId":9862444,"toponymName":"Fort Bragg Travelodge","countryId":"6252001","fcl":"S","population":0,"countryCode":"US","name":"Fort Bragg Travelodge","fclName":"spot, building, farm","adminCodes1":{"ISO3166_2":"CA"},"countryName":"United States","fcodeName":"hotel","adminName1":"California","lat":"39.45006","fcode":"HTL"},{"adminCode1":"NC","lng":"-79.0075","geonameId":7266441,"toponymName":"Fort Bragg","countryId":"6252001","fcl":"S","population":0,"countryCode":"US","name":"Fort Bragg","fclName":"spot, building, farm","adminCodes1":{"ISO3166_2":"NC"},"countryName":"United States","fcodeName":"military installation","adminName1":"North Carolina","lat":"35.13806","fcode":"INSM"},{"adminCode1":"NC","lng":"-78.97419","geonameId":8480713,"toponymName":"Fort Bragg Fire and Emergency Services Station 4","countryId":"6252001","fcl":"S","population":0,"countryCode":"US","name":"Fort Bragg Fire and Emergency Services Station 4","fclName":"spot, building, farm","adminCodes1":{"ISO3166_2":"NC"},"countryName":"United States","fcodeName":"building(s)","adminName1":"North Carolina","lat":"35.15498","fcode":"BLDG"},{"adminCode1":"NC","lng":"-78.93928","geonameId":8480721,"toponymName":"Fort Bragg Fire and Emergency Services Station 2","countryId":"6252001","fcl":"S","population":0,"countryCode":"US","name":"Fort Bragg Fire and Emergency Services Station 2","fclName":"spot, building, farm","adminCodes1":{"ISO3166_2":"NC"},"countryName":"United States","fcodeName":"building(s)","adminName1":"North Carolina","lat":"35.1365","fcode":"BLDG"},{"adminCode1":"NC","lng":"-79.01369","geonameId":8480722,"toponymName":"Fort Bragg Fire and Emergency Services Station 5","countryId":"6252001","fcl":"S","population":0,"countryCode":"US","name":"Fort Bragg Fire and Emergency Services Station 5","fclName":"spot, building, farm","adminCodes1":{"ISO3166_2":"NC"},"countryName":"United States","fcodeName":"building(s)","adminName1":"North Carolina","lat":"35.11777","fcode":"BLDG"},{"adminCode1":"NC","lng":"-78.98005","geonameId":8481575,"toponymName":"Fort Bragg Fire and Emergency Services Headquarters","countryId":"6252001","fcl":"S","population":0,"countryCode":"US","name":"Fort Bragg Fire and Emergency Services Headquarters","fclName":"spot, building, farm","adminCodes1":{"ISO3166_2":"NC"},"countryName":"United States","fcodeName":"building(s)","adminName1":"North Carolina","lat":"35.14083","fcode":"BLDG"},{"adminCode1":"NC","lng":"-78.95582","geonameId":9854323,"toponymName":"Hilton Garden Inn Fayetteville Fort Bragg","countryId":"6252001","fcl":"S","population":0,"countryCode":"US","name":"Hilton Garden Inn Fayetteville Fort Bragg","fclName":"spot, building, farm","adminCodes1":{"ISO3166_2":"NC"},"countryName":"United States","fcodeName":"hotel","adminName1":"North Carolina","lat":"35.07453","fcode":"HTL"},{"adminCode1":"NC","lng":"-79.00991","geonameId":9670439,"toponymName":"Fort Bragg Fire and Emergency Services Station 3","countryId":"6252001","fcl":"S","population":0,"countryCode":"US","name":"Fort Bragg Fire and Emergency Services Station 3","fclName":"spot, building, farm","adminCodes1":{"ISO3166_2":"NC"},"countryName":"United States","fcodeName":"building(s)","adminName1":"North Carolina","lat":"35.14838","fcode":"BLDG"},{"adminCode1":"NC","lng":"-78.92788","geonameId":10338462,"toponymName":"Quality Inn and Suites Fort Bragg","countryId":"6252001","fcl":"S","population":0,"countryCode":"US","name":"Quality Inn and Suites Fort Bragg","fclName":"spot, building, farm","adminCodes1":{"ISO3166_2":"NC"},"countryName":"United States","fcodeName":"hotel","adminName1":"North Carolina","lat":"35.07525","fcode":"HTL"},{"adminCode1":"NC","lng":"-78.96514","geonameId":9855955,"toponymName":"Embassy Suites Fayetteville Fort Bragg","countryId":"6252001","fcl":"S","population":0,"countryCode":"US","name":"Embassy Suites Fayetteville Fort Bragg","fclName":"spot, building, farm","adminCodes1":{"ISO3166_2":"NC"},"countryName":"United States","fcodeName":"hotel","adminName1":"North Carolina","lat":"35.08007","fcode":"HTL"},{"adminCode1":"NC","lng":"-78.96798","geonameId":9855967,"toponymName":"Comfort Inn Near Fort Bragg","countryId":"6252001","fcl":"S","population":0,"countryCode":"US","name":"Comfort Inn Near Fort Bragg","fclName":"spot, building, farm","adminCodes1":{"ISO3166_2":"NC"},"countryName":"United States","fcodeName":"hotel","adminName1":"North Carolina","lat":"35.06679","fcode":"HTL"},{"adminCode1":"NC","lng":"-78.92737","geonameId":9863939,"toponymName":"Knights Inn Fayetteville Fort Bragg","countryId":"6252001","fcl":"S","population":0,"countryCode":"US","name":"Knights Inn Fayetteville Fort Bragg","fclName":"spot, building, farm","adminCodes1":{"ISO3166_2":"NC"},"countryName":"United States","fcodeName":"hotel","adminName1":"North Carolina","lat":"35.07433","fcode":"HTL"},{"adminCode1":"NC","lng":"-78.97306","geonameId":9863940,"toponymName":"Super 8 Spring Lake Fort Bragg","countryId":"6252001","fcl":"S","population":0,"countryCode":"US","name":"Super 8 Spring Lake Fort Bragg","fclName":"spot, building, farm","adminCodes1":{"ISO3166_2":"NC"},"countryName":"United States","fcodeName":"hotel","adminName1":"North Carolina","lat":"35.1629","fcode":"HTL"},{"adminCode1":"NC","lng":"-78.97486","geonameId":10237739,"toponymName":"Super 8 Motel - Spring Lake/ Fort Bragg","countryId":"6252001","fcl":"S","population":0,"countryCode":"US","name":"Super 8 Motel - Spring Lake/ Fort Bragg","fclName":"spot, building, farm","adminCodes1":{"ISO3166_2":"NC"},"countryName":"United States","fcodeName":"hotel","adminName1":"North Carolina","lat":"35.1642","fcode":"HTL"},{"adminCode1":"NC","lng":"-78.969","geonameId":11388778,"toponymName":"Fort Bragg Main Post Cemetary","countryId":"6252001","fcl":"S","population":0,"countryCode":"US","name":"Fort Bragg Main Post Cemetary","fclName":"spot, building, farm","adminCodes1":{"ISO3166_2":"NC"},"countryName":"United States","fcodeName":"cemetery","adminName1":"North Carolina","lat":"35.15729","fcode":"CMTY"},{"adminCode1":"NC","lng":"-78.99586","geonameId":11389582,"toponymName":"Fort Bragg Post Office","countryId":"6252001","fcl":"S","population":0,"countryCode":"US","name":"Fort Bragg Post Office","fclName":"spot, building, farm","adminCodes1":{"ISO3166_2":"NC"},"countryName":"United States","fcodeName":"post office","adminName1":"North Carolina","lat":"35.13036","fcode":"PO"},{"adminCode1":"NC","lng":"-78.98826","geonameId":11389583,"toponymName":"Fort Bragg Macomb Post Office","countryId":"6252001","fcl":"S","population":0,"countryCode":"US","name":"Fort Bragg Macomb Post Office","fclName":"spot, building, farm","adminCodes1":{"ISO3166_2":"NC"},"countryName":"United States","fcodeName":"post office","adminName1":"North Carolina","lat":"35.15255","fcode":"PO"},{"adminCode1":"NC","lng":"-79.33336","geonameId":4487147,"toponymName":"Ranger Station Number 2","countryId":"6252001","fcl":"S","population":0,"countryCode":"US","name":"Ranger Station Number 2","fclName":"spot, building, farm","adminCodes1":{"ISO3166_2":"NC"},"countryName":"United States","fcodeName":"","adminName1":"North Carolina","lat":"35.14933"},{"adminCode1":"NC","lng":"-79.18336","geonameId":4487148,"toponymName":"Ranger Station Number 3","countryId":"6252001","fcl":"S","population":0,"countryCode":"US","name":"Ranger Station Number 3","fclName":"spot, building, farm","adminCodes1":{"ISO3166_2":"NC"},"countryName":"United States","fcodeName":"","adminName1":"North Carolina","lat":"35.18238"},{"adminCode1":"NC","lng":"-79.27059","geonameId":4490232,"toponymName":"Sandy Grove Church","countryId":"6252001","fcl":"S","population":0,"countryCode":"US","name":"Sandy Grove Church","fclName":"spot, building, farm","adminCodes1":{"ISO3166_2":"NC"},"countryName":"United States","fcodeName":"church","adminName1":"North Carolina","lat":"35.05961","fcode":"CH"},{"adminCode1":"NC","lng":"-79.18447","geonameId":4480278,"toponymName":"Morrison Bridge","countryId":"6252001","fcl":"S","population":0,"countryCode":"US","name":"Morrison Bridge","fclName":"spot, building, farm","adminCodes1":{"ISO3166_2":"NC"},"countryName":"United States","fcodeName":"bridge","adminName1":"North Carolina","lat":"35.19238","fcode":"BDG"},{"adminCode1":"NC","lng":"-79.10121","geonameId":4481409,"toponymName":"NC Noname Forty-Four Dam","countryId":"6252001","fcl":"S","population":0,"countryCode":"US","name":"NC Noname Forty-Four Dam","fclName":"spot, building, farm","adminCodes1":{"ISO3166_2":"NC"},"countryName":"United States","fcodeName":"dam","adminName1":"North Carolina","lat":"35.16541","fcode":"DAM"},{"adminCode1":"NC","lng":"-79.25808","geonameId":4481411,"toponymName":"NC Noname Forty-Three Dam","countryId":"6252001","fcl":"S","population":0,"countryCode":"US","name":"NC Noname Forty-Three Dam","fclName":"spot, building, farm","adminCodes1":{"ISO3166_2":"NC"},"countryName":"United States","fcodeName":"dam","adminName1":"North Carolina","lat":"35.18516","fcode":"DAM"},{"adminCode1":"NC","lng":"-79.29642","geonameId":4481416,"toponymName":"NC Noname Thirty-Five Dam","countryId":"6252001","fcl":"S","population":0,"countryCode":"US","name":"NC Noname Thirty-Five Dam","fclName":"spot, building, farm","adminCodes1":{"ISO3166_2":"NC"},"countryName":"United States","fcodeName":"dam","adminName1":"North Carolina","lat":"35.17849","fcode":"DAM"},{"adminCode1":"NC","lng":"-79.20809","geonameId":4481417,"toponymName":"NC Noname Thirty-Four Dam","countryId":"6252001","fcl":"S","population":0,"countryCode":"US","name":"NC Noname Thirty-Four Dam","fclName":"spot, building, farm","adminCodes1":{"ISO3166_2":"NC"},"countryName":"United States","fcodeName":"dam","adminName1":"North Carolina","lat":"35.05183","fcode":"DAM"},{"adminCode1":"NC","lng":"-79.2517","geonameId":4481418,"toponymName":"NC Noname Thirty-Six Dam","countryId":"6252001","fcl":"S","population":0,"countryCode":"US","name":"NC Noname Thirty-Six Dam","fclName":"spot, building, farm","adminCodes1":{"ISO3166_2":"NC"},"countryName":"United States","fcodeName":"dam","adminName1":"North Carolina","lat":"35.09627","fcode":"DAM"},{"adminCode1":"NC","lng":"-79.12031","geonameId":4477223,"toponymName":"Longstreet Church","countryId":"6252001","fcl":"S","population":0,"countryCode":"US","name":"Longstreet Church","fclName":"spot, building, farm","adminCodes1":{"ISO3166_2":"NC"},"countryName":"United States","fcodeName":"church","adminName1":"North Carolina","lat":"35.12211","fcode":"CH"},{"adminCode1":"NC","lng":"-79.33642","geonameId":4468535,"toponymName":"Graham City Lake Number One Dam","countryId":"6252001","fcl":"S","population":0,"countryCode":"US","name":"Graham City Lake Number One Dam","fclName":"spot, building, farm","adminCodes1":{"ISO3166_2":"NC"},"countryName":"United States","fcodeName":"dam","adminName1":"North Carolina","lat":"35.09516","fcode":"DAM"},{"adminCode1":"NC","lng":"-79.31086","geonameId":4828805,"toponymName":"Goins Cemetery","countryId":"6252001","fcl":"S","population":0,"countryCode":"US","name":"Goins Cemetery","fclName":"spot, building, farm","adminCodes1":{"ISO3166_2":"NC"},"countryName":"United States","fcodeName":"cemetery","adminName1":"North Carolina","lat":"35.16516","fcode":"CMTY"},{"adminCode1":"CA","lng":"-123.8047","geonameId":6480444,"toponymName":"Americas Best Value Inn","countryId":"6252001","fcl":"S","population":0,"countryCode":"US","name":"Americas Best Value Inn","fclName":"spot, building, farm","adminCodes1":{"ISO3166_2":"CA"},"countryName":"United States","fcodeName":"hotel","adminName1":"California","lat":"39.4304","fcode":"HTL"},{"adminCode1":"CA","lng":"-123.8141","geonameId":6500181,"toponymName":"Pine Beach Inn","countryId":"6252001","fcl":"S","population":0,"countryCode":"US","name":"Pine Beach Inn","fclName":"spot, building, farm","adminCodes1":{"ISO3166_2":"CA"},"countryName":"United States","fcodeName":"hotel","adminName1":"California","lat":"39.3833","fcode":"HTL"},{"adminCode1":"CA","lng":"-123.8064","geonameId":6509383,"toponymName":"Best Western Vista Manor Lodge","countryId":"6252001","fcl":"S","population":0,"countryCode":"US","name":"Best Western Vista Manor Lodge","fclName":"spot, building, farm","adminCodes1":{"ISO3166_2":"CA"},"countryName":"United States","fcodeName":"hotel","adminName1":"California","lat":"39.4599","fcode":"HTL"},{"adminCode1":"CA","lng":"-123.803","geonameId":6511534,"toponymName":"The Lodge At Noyo River","countryId":"6252001","fcl":"S","population":0,"countryCode":"US","name":"The Lodge At Noyo River","fclName":"spot, building, farm","adminCodes1":{"ISO3166_2":"CA"},"countryName":"United States","fcodeName":"hotel","adminName1":"California","lat":"39.4268","fcode":"HTL"},{"adminCode1":"CA","lng":"-123.806","geonameId":6497538,"toponymName":"The Beach House Inn","countryId":"6252001","fcl":"S","population":0,"countryCode":"US","name":"The Beach House Inn","fclName":"spot, building, farm","adminCodes1":{"ISO3166_2":"CA"},"countryName":"United States","fcodeName":"hotel","adminName1":"California","lat":"39.456","fcode":"HTL"},{"adminCode1":"CA","lng":"-123.8059","geonameId":6524677,"toponymName":"Quality Inn And Stes Tradewind","countryId":"6252001","fcl":"S","population":0,"countryCode":"US","name":"Quality Inn And Stes Tradewind","fclName":"spot, building, farm","adminCodes1":{"ISO3166_2":"CA"},"countryName":"United States","fcodeName":"hotel","adminName1":"California","lat":"39.4378","fcode":"HTL"}]}
